{
	"ENMITY_ADDON_FAILED": "Failed to load addon: {error}",
	"ENMITY_ADDON_NO_DESCRIPTION": "No description provided.",
	"ENMITY_ASSET_BROWSER": "Asset Browser",
	"ENMITY_CHANGE_RESTART": "Restart Required",
	"ENMITY_CHANGE_RESTART_DESC": "This change requires a restart to apply. Would you like to restart?",
	"ENMITY_DEBUG_BRIDGE": "Debug Bridge",
	"ENMITY_DEBUG_BRIDGE_DESC": "Automatically connects to a specified remote debug bridge to allow for code evaluation.",
	"ENMITY_DEBUG_BRIDGE_IP": "Debug IP",
	"ENMITY_DEBUG_LOGS": "Debug Logs",
	"ENMITY_DEVELOPMENT_SETTINGS": "Development Settings",
	"ENMITY_ENABLED": "Enabled",
	"ENMITY_ERROR_BOUNDARY": "Error Boundary",
	"ENMITY_ERROR_BOUNDARY_DESC": "Crash recovery module. Do not disable if you are a consumer.",
	"ENMITY_GENERAL": "General",
	"ENMITY_INSTALL": "Install",
	"ENMITY_INSTALL_TITLE": "Install {type}",
	"ENMITY_LOADER": "Loader",
	"ENMITY_LOADER_CUSTOM_BUNDLE": "Custom Bundle URL",
	"ENMITY_LOADER_DEVTOOLS": "React DevTools",
	"ENMITY_LOADER_DEVTOOLS_DESC": "Enables remote developer tools that can be accessed from a desktop.",
	"ENMITY_LOADER_ENABLED_DESC": "Handles the loading of Enmity. You will need to edit the configuration file to enable the loader again.",
	"ENMITY_LOADER_UPDATER_FORCE": "Force Update",
	"ENMITY_LOADER_UPDATER_FORCE_DESC": "Always fetches and uses the latest bundle available at the provided bundle URL.",
	"ENMITY_MISC": "Misc",
	"ENMITY_MODULE_SETTINGS": "Module Settings",
	"ENMITY_PLUGINS": "Plugins",
	"ENMITY_RECOVERY_MODE": "Recovery Mode",
	"ENMITY_RECOVERY_MODE_DESC": "Avoids loading addons to prevent crashing.",
	"ENMITY_RECOVERY_MODE_ENABLED": "Recovery mode is enabled, all addons have been disabled to aid you in the diagnosis of issues.",
	"ENMITY_RESTART": "Restart",
	"ENMITY_SEARCH_ASSETS": "Search assets...",
	"ENMITY_SEARCH_PLUGINS": "Search plugins...",
	"ENMITY_SEARCH_THEMES": "Search themes...",
	"ENMITY_STATS": "Stats",
	"ENMITY_THEMES": "Themes",
	"ENMITY_THEME_EDITOR": "Theme Editor",
	"ENMITY_THEME_GET_DESC": "Would you like to create a theme, or import one?",
	"ENMITY_THEME_GET_OPTION_CREATE": "Create",
	"ENMITY_THEME_GET_OPTION_IMPORT": "Import",
	"ENMITY_TOAST_SETTINGS": "Toast Settings",
	"ENMITY_UPDATER": "Updater"
}